rigger/__init__.py
rigger/_loader.py
rigger/core.py
rigger/fixtures/address
rigger/fixtures/area
rigger/fixtures/color
rigger/fixtures/domain
rigger/fixtures/family
rigger/fixtures/fgiven
rigger/fixtures/mgiven
rigger/fixtures/noun
rigger/fixtures/phone
tests/__init__.py
tests/test_identity.py
rigger-0.0.2.dist-info/AUTHORS.rst
rigger-0.0.2.dist-info/LICENSE
rigger-0.0.2.dist-info/METADATA
rigger-0.0.2.dist-info/WHEEL
rigger-0.0.2.dist-info/top_level.txt
rigger-0.0.2.dist-info/RECORD
