Metadata-Version: 2.1
Name: rigger
Version: 0.0.2
Summary: Generates modern random idenities, inspired by unix 'rig'
Home-page: https://github.com/cgdeboer/rigger
Author: Calvin DeBoer
Author-email: cgdeboer@gmail.com
License: UNKNOWN
Platform: UNKNOWN
Classifier: Programming Language :: Python :: 3
Classifier: License :: OSI Approved :: MIT License
Classifier: Operating System :: OS Independent
